buzzquiz/__init__.py
buzzquiz/buzz.py
buzzquiz/controllers.py
buzzquiz/games.py
buzzquiz/lights.py
buzzquiz/reader.py
buzzquiz-0.1.0.dist-info/LICENSE
buzzquiz-0.1.0.dist-info/METADATA
buzzquiz-0.1.0.dist-info/WHEEL
buzzquiz-0.1.0.dist-info/RECORD
