Metadata-Version: 2.1
Name: buzzquiz
Version: 0.1.0
Summary: Handle the controllers of PS2 Buzz!
License: GNU GENERAL PUBLIC LICENSE
Author: angmorpri
Author-email: angelmorenoprieto@gmail.com
Requires-Python: >=3.10,<4.0
Classifier: License :: Other/Proprietary License
Classifier: Programming Language :: Python :: 3
Classifier: Programming Language :: Python :: 3.10
Classifier: Programming Language :: Python :: 3.11
Classifier: Programming Language :: Python :: 3.12
Requires-Dist: hidapi (>=0.14.0.post2,<0.15.0)
